<?xml version="1.0" encoding="UTF-8"?>
<line description="Vogtland">
	<coordinate>
		<lon>11.905934173825386</lon>
		<lat>50.25559673220218</lat>
	</coordinate>
	<coordinate>
		<lon>12.050654561108644</lon>
		<lat>50.27858254281341</lat>
	</coordinate>
	<coordinate>
		<lon>12.100720867135209</lon>
		<lat>50.31150079988038</lat>
	</coordinate>
	<coordinate>
		<lon>12.166702364612433</lon>
		<lat>50.32773936120179</lat>
	</coordinate>
	<coordinate>
		<lon>12.204263186911845</lon>
		<lat>50.300022175543404</lat>
	</coordinate>
	<coordinate>
		<lon>12.248833217917934</lon>
		<lat>50.27058043981498</lat>
	</coordinate>
	<coordinate>
		<lon>12.262056318039981</lon>
		<lat>50.231927141944595</lat>
	</coordinate>
	<coordinate>
		<lon>12.285258581701328</lon>
		<lat>50.1858414412408</lat>
	</coordinate>
	<coordinate>
		<lon>12.312652428507107</lon>
		<lat>50.16697267079482</lat>
	</coordinate>
	<coordinate>
		<lon>12.34168377791417</lon>
		<lat>50.16897722937543</lat>
	</coordinate>
	<coordinate>
		<lon>12.340378328455358</lon>
		<lat>50.22240179136159</lat>
	</coordinate>
	<coordinate>
		<lon>12.368556390841093</lon>
		<lat>50.25585259433154</lat>
	</coordinate>
	<coordinate>
		<lon>12.417781146375262</lon>
		<lat>50.314048380918194</lat>
	</coordinate>
	<coordinate>
		<lon>12.473273245574859</lon>
		<lat>50.34585577709203</lat>
	</coordinate>
	<coordinate>
		<lon>12.550621656416638</lon>
		<lat>50.3841515893443</lat>
	</coordinate>
	<coordinate>
		<lon>12.664513848946427</lon>
		<lat>50.41023887268008</lat>
	</coordinate>
	<coordinate>
		<lon>12.732302320960969</lon>
		<lat>50.41667686516965</lat>
	</coordinate>
	<coordinate>
		<lon>12.696816748126736</lon>
		<lat>50.45017618245035</lat>
	</coordinate>
	<coordinate>
		<lon>12.589739502645102</lon>
		<lat>50.51828373341607</lat>
	</coordinate>
	<coordinate>
		<lon>12.479697182506868</lon>
		<lat>50.583674615347434</lat>
	</coordinate>
	<coordinate>
		<lon>12.385737252013968</lon>
		<lat>50.67311438195327</lat>
	</coordinate>
	<coordinate>
		<lon>12.274112518699525</lon>
		<lat>50.76952775304301</lat>
	</coordinate>
	<coordinate>
		<lon>12.313958415885338</lon>
		<lat>50.81163146989644</lat>
	</coordinate>
	<coordinate>
		<lon>12.3421956444123</lon>
		<lat>50.85136116172657</lat>
	</coordinate>
	<coordinate>
		<lon>12.297650813919063</lon>
		<lat>50.88265708340592</lat>
	</coordinate>
	<coordinate>
		<lon>12.203609462016288</lon>
		<lat>50.90998852502699</lat>
	</coordinate>
	<coordinate>
		<lon>12.094819504769731</lon>
		<lat>50.92753439430146</lat>
	</coordinate>
	<coordinate>
		<lon>12.00937577417568</lon>
		<lat>50.918232229251345</lat>
	</coordinate>
	<coordinate>
		<lon>11.923704134120982</lon>
		<lat>50.87603494886616</lat>
	</coordinate>
	<coordinate>
		<lon>11.88985058432516</lon>
		<lat>50.75845173442036</lat>
	</coordinate>
	<coordinate>
		<lon>11.861200202430751</lon>
		<lat>50.707730376862486</lat>
	</coordinate>
	<coordinate>
		<lon>11.710856019025613</lon>
		<lat>50.66465418736277</lat>
	</coordinate>
	<coordinate>
		<lon>11.63235765592077</lon>
		<lat>50.63234373483576</lat>
	</coordinate>
	<coordinate>
		<lon>11.60034542267232</lon>
		<lat>50.57383385385222</lat>
	</coordinate>
	<coordinate>
		<lon>11.607179830780922</lon>
		<lat>50.48022710201647</lat>
	</coordinate>
	<coordinate>
		<lon>11.658465231176137</lon>
		<lat>50.415442422768905</lat>
	</coordinate>
	<coordinate>
		<lon>11.723466496007688</lon>
		<lat>50.33400310209254</lat>
	</coordinate>
	<coordinate>
		<lon>11.82673790664424</lon>
		<lat>50.28411092714319</lat>
	</coordinate>
	<coordinate>
		<lon>11.905666648273723</lon>
		<lat>50.25735824121455</lat>
	</coordinate>
</line>